{"states":[{"name":"Bagmati Province","code":"P3"},{"name":"Sudurpashchim Province","code":"P7"},{"name":"Lumbini Province","code":"P5"},{"name":"Koshi Province","code":"P1"},{"name":"Madhesh Province","code":"P2"},{"name":"Gandaki Province","code":"P4"},{"name":"Karnali Province","code":"P6"}],"districts":{"P3":[{"name":"Sindhuli","stateCode":"P3"},{"name":"Ramechhap","stateCode":"P3"},{"name":"Dolakha","stateCode":"P3"},{"name":"Bhaktapur","stateCode":"P3"},{"name":"Dhading","stateCode":"P3"},{"name":"Kathmandu","stateCode":"P3"},{"name":"Kavrepalanchok","stateCode":"P3"},{"name":"Lalitpur","stateCode":"P3"},{"name":"Nuwakot","stateCode":"P3"},{"name":"Rasuwa","stateCode":"P3"},{"name":"Sindhupalchok","stateCode":"P3"},{"name":"Chitwan","stateCode":"P3"},{"name":"Makwanpur","stateCode":"P3"}],"P7":[{"name":"Achham","stateCode":"P7"},{"name":"Baitadi","stateCode":"P7"},{"name":"Bajhang","stateCode":"P7"},{"name":"Bajura","stateCode":"P7"},{"name":"Dadeldhura","stateCode":"P7"},{"name":"Darchula","stateCode":"P7"},{"name":"Doti","stateCode":"P7"},{"name":"Kailali","stateCode":"P7"},{"name":"Kanchanpur","stateCode":"P7"}],"P5":[{"name":"Kapilvastu","stateCode":"P5"},{"name":"Rupandehi","stateCode":"P5"},{"name":"Arghakhanchi","stateCode":"P5"},{"name":"Gulmi","stateCode":"P5"},{"name":"Palpa","stateCode":"P5"},{"name":"Dang","stateCode":"P5"},{"name":"Pyuthan","stateCode":"P5"},{"name":"Rolpa","stateCode":"P5"},{"name":"Eastern-rukum","stateCode":"P5"},{"name":"Banke","stateCode":"P5"},{"name":"Bardiya","stateCode":"P5"}],"P1":[{"name":"Bhojpur","stateCode":"P1"},{"name":"Dhankuta","stateCode":"P1"},{"name":"Illam","stateCode":"P1"},{"name":"Jhapa","stateCode":"P1"},{"name":"Khotang","stateCode":"P1"},{"name":"Morang","stateCode":"P1"},{"name":"Okhaldhunga","stateCode":"P1"},{"name":"Panchthar","stateCode":"P1"},{"name":"Sankhuwasabha","stateCode":"P1"},{"name":"Solukhumbu","stateCode":"P1"},{"name":"Sunsari","stateCode":"P1"},{"name":"Taplejung","stateCode":"P1"},{"name":"Tehrathum","stateCode":"P1"},{"name":"Udayapur","stateCode":"P1"}],"P2":[{"name":"Sarlahi","stateCode":"P2"},{"name":"Dhanusha","stateCode":"P2"},{"name":"Bara","stateCode":"P2"},{"name":"Rautahat","stateCode":"P2"},{"name":"Saptari","stateCode":"P2"},{"name":"Siraha","stateCode":"P2"},{"name":"Mahottari","stateCode":"P2"},{"name":"Parsa","stateCode":"P2"},{"name":"Parasi","stateCode":"P2"}],"P4":[{"name":"Baglung","stateCode":"P4"},{"name":"Gorkha","stateCode":"P4"},{"name":"Kaski","stateCode":"P4"},{"name":"Lamjung","stateCode":"P4"},{"name":"Manang","stateCode":"P4"},{"name":"Mustang","stateCode":"P4"},{"name":"Myagdi","stateCode":"P4"},{"name":"Nawalpur","stateCode":"P4"},{"name":"Parbat","stateCode":"P4"},{"name":"Syangja","stateCode":"P4"},{"name":"Tanahun","stateCode":"P4"}],"P6":[{"name":"Western-rukum","stateCode":"P6"},{"name":"Salyan","stateCode":"P6"},{"name":"Dolpa","stateCode":"P6"},{"name":"Humla","stateCode":"P6"},{"name":"Jumla","stateCode":"P6"},{"name":"Kalikot","stateCode":"P6"},{"name":"Mugu","stateCode":"P6"},{"name":"Surkhet","stateCode":"P6"},{"name":"Dailekh","stateCode":"P6"},{"name":"Jajarkot","stateCode":"P6"}]},"areas":{"P3__Sindhuli":[{"name":"Marin Rural Municipality"},{"name":"Phikkal Rural Municipality"},{"name":"Tinpatan Rural Municipality"},{"name":"Sunkoshi Rural Municipality"},{"name":"Golanjor Rural Municipality"},{"name":"Ghanglekh Rural Municipality"},{"name":"Hariharpurgadhi Rural Municipality"},{"name":"Dudhouli Municipality"},{"name":"Kamalamai Municipality"}],"P3__Ramechhap":[{"name":"Bigu Rural Municipality"},{"name":"Sailung Rural Municipality"},{"name":"Melung Rural Municipality"},{"name":"Baiteshwor Rural Municipality"},{"name":"Tamakoshi Rural Municipality"},{"name":"Gaurishankar Rural Municipality"},{"name":"Kalinchok Rural Municipality"},{"name":"Jiri Municipality"},{"name":"Bhimeshwor Municipality"}],"P3__Dolakha":[{"name":"Marin Rural Municipality"},{"name":"Phikkal Rural Municipality"},{"name":"Tinpatan Rural Municipality"},{"name":"Sunkoshi Rural Municipality"},{"name":"Golanjor Rural Municipality"},{"name":"Ghanglekh Rural Municipality"},{"name":"Hariharpurgadhi Rural Municipality"},{"name":"Dudhouli Municipality"},{"name":"Kamalamai Municipality"}],"P3__Bhaktapur":[{"name":"Changunarayan Municipality"},{"name":"Suryabinayak Municipality"},{"name":"Bhaktapur Municipality"},{"name":"Madhyapur Thimi Municipality"}],"P3__Dhading":[{"name":"Gajuri Rural Municipality"},{"name":"Galchi Rural Municipality"},{"name":"Thakre Rural Municipality"},{"name":"Siddhalek Rural Municipality"},{"name":"Khaniyabash Rural Municipality"},{"name":"Jwalamukhi Rural Municipality"},{"name":"Gangajamuna Rural Municipality"},{"name":"Rubi Valley Rural Municipality"},{"name":"Tripura Sundari Rural Municipality"},{"name":"Netrawati Dabjong Rural Municipality"},{"name":"Benighat Rorang Rural Municipality"},{"name":"Nilakantha Municipality"},{"name":"Dhunibesi Municipality"}],"P3__Kathmandu":[{"name":"Kirtipur Municipality"},{"name":"Shankharapur Municipality"},{"name":"Nagarjun Municipality"},{"name":"Kageshwori Manahora Municipality"},{"name":"Dakshinkali Municipality"},{"name":"Budhanilakantha Municipality"},{"name":"Tarakeshwor Municipality"},{"name":"Kathmandu Metropolitian City"},{"name":"Tokha Municipality"},{"name":"Chandragiri Municipality"},{"name":"Gokarneshwor Municipality"}],"P3__Kavrepalanchok":[{"name":"Roshi Rural Municipality"},{"name":"Temal Rural Municipality"},{"name":"Bhumlu Rural Municipality"},{"name":"Mahabharat Rural Municipality"},{"name":"Bethanchowk Rural Municipality"},{"name":"Khanikhola Rural Municipality"},{"name":"Chaurideurali Rural Municipality"},{"name":"Banepa Municipality"},{"name":"Mandandeupur Municipality"},{"name":"Dhulikhel Municipality"},{"name":"Panauti Municipality"},{"name":"Namobuddha Municipality"},{"name":"Panchkhal Municipality"}],"P3__Lalitpur":[{"name":"Bagmati Rural Municipality"},{"name":"Mahankal Rural Municipality"},{"name":"Konjyosom Rural Municipality"},{"name":"Lalitpur Metropolitian City"},{"name":"Mahalaxmi Municipality"},{"name":"Godawari Municipality"}],"P3__Nuwakot":[{"name":"Kakani Rural Municipality"},{"name":"Tadi Rural Municipality"},{"name":"Likhu Rural Municipality"},{"name":"Myagang Rural Municipality"},{"name":"Shivapuri Rural Municipality"},{"name":"Kispang Rural Municipality"},{"name":"Suryagadhi Rural Municipality"},{"name":"Tarkeshwar Rural Municipality"},{"name":"Panchakanya Rural Municipality"},{"name":"Dupcheshwar Rural Municipality"},{"name":"Belkotgadhi Municipality"},{"name":"Bidur Municipality"}],"P3__Rasuwa":[{"name":"Kalika Rural Municipality"},{"name":"Naukunda Rural Municipality"},{"name":"Uttargaya Rural Municipality"},{"name":"Gosaikunda Rural Municipality"},{"name":"Amachodingmo Rural Municipality"}],"P3__Sindhupalchok":[{"name":"Jugal Rural Municipality"},{"name":"Balefi Rural Municipality"},{"name":"Sunkoshi Rural Municipality"},{"name":"Helambu Rural Municipality"},{"name":"Bhotekoshi Rural Municipality"},{"name":"Lisangkhu Pakhar Rural Municipality"},{"name":"Indrawati Rural Municipality"},{"name":"Tripurasundari Rural Municipality"},{"name":"Panchpokhari Thangpal Rural Municipality"},{"name":"Chautara Sangachokgadhi Municipality"},{"name":"Barhabise Municipality"},{"name":"Melamchi Municipality"}],"P3__Chitwan":[{"name":"Ichchhyakamana Rural Municipality"},{"name":"Bharatpur Metropolitian City"},{"name":"Kalika Municipality"},{"name":"Khairahani Municipality"},{"name":"Madi Municipality"},{"name":"Rapti Municipality"},{"name":"Ratnanagar Municipality"}],"P3__Makwanpur":[{"name":"Bakaiya Rural Municipality"},{"name":"Kailash Rural Municipality"},{"name":"Manahari Rural Municipality"},{"name":"Bhimphedi Rural Municipality"},{"name":"Bagmati Rural Municipality"},{"name":"Raksirang Rural Municipality"},{"name":"Makawanpurgadhi Rural Municipality"},{"name":"Indrasarowar Rural Municipality"},{"name":"Hetauda Sub-metropolitian City"},{"name":"Thaha Municipality"}],"P7__Achham":[{"name":"Dhakari Rural Municipality"},{"name":"Mellekh Rural Municipality"},{"name":"Chaurpati Rural Municipality"},{"name":"Ramaroshan Rural Municipality"},{"name":"Turmakhad Rural Municipality"},{"name":"Bannigadhi Jayagadh Rural Municipality"},{"name":"Sanphebagar Municipality"},{"name":"Mangalsen Municipality"},{"name":"Kamalbazar Municipality"},{"name":"Panchadewal Binayak Municipality"}],"P7__Baitadi":[{"name":"Sigas Rural Municipality"},{"name":"Shivanath Rural Municipality"},{"name":"Surnaya Rural Municipality"},{"name":"Dilasaini Rural Municipality"},{"name":"Pancheshwar Rural Municipality"},{"name":"Dogadakedar Rural Municipality"},{"name":"Melauli Municipality"},{"name":"Dasharathchanda Municipality"},{"name":"Purchaudi Municipality"},{"name":"Patan Municipality"}],"P7__Bajhang":[{"name":"Masta Rural Municipality"},{"name":"Thalara Rural Municipality"},{"name":"Talkot Rural Municipality"},{"name":"Surma Rural Municipality"},{"name":"Saipaal Rural Municipality"},{"name":"Durgathali Rural Municipality"},{"name":"Bithadchir Rural Municipality"},{"name":"Kedarseu Rural Municipality"},{"name":"Khaptadchhanna Rural Municipality"},{"name":"Chabispathivera Rural Municipality"},{"name":"Jayaprithivi Municipality"},{"name":"Bungal Municipality"}],"P7__Bajura":[{"name":"Gaumul Rural Municipality"},{"name":"Himali Rural Municipality"},{"name":"Jagannath Rural Municipality"},{"name":"Khaptad Chhededaha Rural Municipality"},{"name":"Swami Kartik Khaapar Rural Municipality"},{"name":"Badimalika Municipality"},{"name":"Tribeni Municipality"},{"name":"Budhiganga Municipality"},{"name":"Budhinanda Municipality"}],"P7__Dadeldhura":[{"name":"Alital Rural Municipality"},{"name":"Ajaymeru Rural Municipality"},{"name":"Bhageshwar Rural Municipality"},{"name":"Nawadurga Rural Municipality"},{"name":"Ganayapdhura Rural Municipality"},{"name":"Amargadhi Municipality"},{"name":"Parashuram Municipality"}],"P7__Darchula":[{"name":"Lekam Rural Municipality"},{"name":"Naugad Rural Municipality"},{"name":"Byas Rural Municipality"},{"name":"Dunhu Rural Municipality"},{"name":"Marma Rural Municipality"},{"name":"Apihimal Rural Municipality"},{"name":"Malikaarjun Rural Municipality"},{"name":"Mahakali Municipality"},{"name":"Shailyashikhar Municipality"}],"P7__Doti":[{"name":"Sayal Rural Municipality"},{"name":"Adharsha Rural Municipality"},{"name":"Jorayal Rural Municipality"},{"name":"Badikedar Rural Municipality"},{"name":"Purbichauki Rural Municipality"},{"name":"K I Singh Rural Municipality"},{"name":"Bogtan Foodsil Rural Municipality"},{"name":"Dipayal Silgadi Municipality"},{"name":"Shikhar Municipality"}],"P7__Kailali":[{"name":"Chure Rural Municipality"},{"name":"Janaki Rural Municipality"},{"name":"Kailari Rural Municipality"},{"name":"Joshipur Rural Municipality"},{"name":"Mohanyal Rural Municipality"},{"name":"Bardagoriya Rural Municipality"},{"name":"Tikapur Municipality"},{"name":"Ghodaghodi Municipality"},{"name":"Bhajani Municipality"},{"name":"Dhangadhi Sub-metropolitian City"},{"name":"Gauriganga Municipality"},{"name":"Godawari Municipality"},{"name":"Lamkichuha Municipality"}],"P7__Kanchanpur":[{"name":"Beldandi Rural Municipality"},{"name":"Laljhadi Rural Municipality"},{"name":"Punarbas Municipality"},{"name":"Krishnapur Municipality"},{"name":"Mahakali Municipality"},{"name":"Bedkot Municipality"},{"name":"Belauri Municipality"},{"name":"Bhimdatta Municipality"},{"name":"Shuklaphanta Municipality"}],"P5__Kapilvastu":[{"name":"Yashodhara Rural Municipality"},{"name":"Bijayanagar Rural Municipality"},{"name":"Mayadevi Rural Municipality"},{"name":"Suddhodhan Rural Municipality"},{"name":"Shivaraj Municipality"},{"name":"Kapilbastu Municipality"},{"name":"Buddhabhumi Municipality"},{"name":"Maharajgunj Municipality"},{"name":"Banganga Municipality"},{"name":"Krishnanagar Municipality"}],"P5__Rupandehi":[{"name":"Kanchan Rural Municipality"},{"name":"Siyari Rural Municipality"},{"name":"Rohini Rural Municipality"},{"name":"Gaidahawa Rural Municipality"},{"name":"Omsatiya Rural Municipality"},{"name":"Sudhdhodhan Rural Municipality"},{"name":"Mayadevi Rural Municipality"},{"name":"Marchawari Rural Municipality"},{"name":"Kotahimai Rural Municipality"},{"name":"Sammarimai Rural Municipality"},{"name":"Butwal Sub-metropolitian City"},{"name":"Lumbini Sanskritik Municipality"},{"name":"Devdaha Municipality"},{"name":"Sainamaina Municipality"},{"name":"Siddharthanagar Municipality"},{"name":"Tillotama Municipality"}],"P5__Arghakhanchi":[{"name":"Panini Rural Municipality"},{"name":"Chhatradev Rural Municipality"},{"name":"Malarani Rural Municipality"},{"name":"Bhumekasthan Municipality"},{"name":"Sitganga Municipality"},{"name":"Sandhikharka Municipality"}],"P5__Gulmi":[{"name":"Ruru Rural Municipality"},{"name":"Isma Rural Municipality"},{"name":"Madane Rural Municipality"},{"name":"Malika Rural Municipality"},{"name":"Chatrakot Rural Municipality"},{"name":"Dhurkot Rural Municipality"},{"name":"Satyawati Rural Municipality"},{"name":"Chandrakot Rural Municipality"},{"name":"Kaligandaki Rural Municipality"},{"name":"Gulmidarbar Rural Municipality"},{"name":"Resunga Municipality"},{"name":"Musikot Municipality"}],"P5__Palpa":[{"name":"Rambha Rural Municipality"},{"name":"Tinau Rural Municipality"},{"name":"Nisdi Rural Municipality"},{"name":"Mathagadhi Rural Municipality"},{"name":"Ribdikot Rural Municipality"},{"name":"Purbakhola Rural Municipality"},{"name":"Bagnaskali Rural Municipality"},{"name":"Rainadevi Chhahara Rural Municipality"},{"name":"Tansen Municipality"},{"name":"Rampur Municipality"}],"P5__Dang":[{"name":"Babai Rural Municipality"},{"name":"Gadhawa Rural Municipality"},{"name":"Rapti Rural Municipality"},{"name":"Rajpur Rural Municipality"},{"name":"Dangisharan Rural Municipality"},{"name":"Shantinagar Rural Municipality"},{"name":"Banglachuli Rural Municipality"},{"name":"Tulsipur Sub-metropolitian City"},{"name":"Ghorahi Sub-metropolitian City"},{"name":"Lamahi Municipality"}],"P5__Pyuthan":[{"name":"Ayirabati Rural Municipality"},{"name":"Gaumukhi Rural Municipality"},{"name":"Jhimruk Rural Municipality"},{"name":"Naubahini Rural Municipality"},{"name":"Mandavi Rural Municipality"},{"name":"Mallarani Rural Municipality"},{"name":"Sarumarani Rural Municipality"},{"name":"Pyuthan Municipality"},{"name":"Sworgadwary Municipality"}],"P5__Rolpa":[{"name":"Madi Rural Municipality"},{"name":"Thawang Rural Municipality"},{"name":"Sunchhahari Rural Municipality"},{"name":"Lungri Rural Municipality"},{"name":"Gangadev Rural Municipality"},{"name":"Tribeni Rural Municipality"},{"name":"Pariwartan Rural Municipality"},{"name":"Runtigadi Rural Municipality"},{"name":"Sunil Smriti Rural Municipality"},{"name":"Rolpa Municipality"}],"P5__Eastern-rukum":[{"name":"Bhume Rural Municipality"},{"name":"Sisne Rural Municipality"},{"name":"Putha Uttarganga Rural Municipality"}],"P5__Banke":[{"name":"Khajura Rural Municipality"},{"name":"Janki Rural Municipality"},{"name":"Baijanath Rural Municipality"},{"name":"Duduwa Rural Municipality"},{"name":"Narainapur Rural Municipality"},{"name":"Rapti Sonari Rural Municipality"},{"name":"Kohalpur Municipality"},{"name":"Nepalgunj Sub-metropolitian City"}],"P5__Bardiya":[{"name":"Geruwa Rural Municipality"},{"name":"Badhaiyatal Rural Municipality"},{"name":"Thakurbaba Municipality"},{"name":"Bansagadhi Municipality"},{"name":"Barbardiya Municipality"},{"name":"Rajapur Municipality"},{"name":"Madhuwan Municipality"},{"name":"Gulariya Municipality"}],"P1__Bhojpur":[{"name":"Arun Rural Municipality"},{"name":"Aamchowk Rural Municipality"},{"name":"Hatuwagadhi Rural Municipality"},{"name":"Pauwadungma Rural Municipality"},{"name":"Temkemaiyung Rural Municipality"},{"name":"Salpasilichho Rural Municipality"},{"name":"Ramprasad Rai Rural Municipality"},{"name":"Shadananda Municipality"},{"name":"Bhojpur Municipality"}],"P1__Dhankuta":[{"name":"Chaubise Rural Municipality"},{"name":"Shahidbhumi Rural Municipality"},{"name":"Sangurigadhi Rural Municipality"},{"name":"Chhathar Jorpati Rural Municipality"},{"name":"Pakhribas Municipality"},{"name":"Mahalaxmi Municipality"},{"name":"Dhankuta Municipality"}],"P1__Illam":[{"name":"Rong Rural Municipality"},{"name":"Mangsebung Rural Municipality"},{"name":"Chulachuli Rural Municipality"},{"name":"Sandakpur Rural Municipality"},{"name":"Fakphokthum Rural Municipality"},{"name":"Maijogmai Rural Municipality"},{"name":"Illam Municipality"},{"name":"Mai Municipality"},{"name":"Deumai Municipality"},{"name":"Suryodaya Municipality"}],"P1__Jhapa":[{"name":"Kamal Rural Municipality"},{"name":"Jhapa Rural Municipality"},{"name":"Kachankawal Rural Municipality"},{"name":"Gauriganj Rural Municipality"},{"name":"Barhadashi Rural Municipality"},{"name":"Haldibari Rural Municipality"},{"name":"Buddhashanti Rural Municipality"},{"name":"Shivasataxi Municipality"},{"name":"Bhadrapur Municipality"},{"name":"Kankai Municipality"},{"name":"Birtamod Municipality"},{"name":"Mechinagar Municipality"},{"name":"Damak Municipality"},{"name":"Arjundhara Municipality"},{"name":"Gauradhaha Municipality"}],"P1__Khotang":[{"name":"Sakela Rural Municipality"},{"name":"Khotehang Rural Municipality"},{"name":"Barahapokhari Rural Municipality"},{"name":"Ainselukhark Rural Municipality"},{"name":"Rawa Besi Rural Municipality"},{"name":"Kepilasagadhi Rural Municipality"},{"name":"Jantedhunga Rural Municipality"},{"name":"Diprung Chuichumma Rural Municipality"},{"name":"Halesi Tuwachung Municipality"},{"name":"Diktel Rupakot Majhuwagadhi Municipality"}],"P1__Morang":[{"name":"Jahada Rural Municipality"},{"name":"Katahari Rural Municipality"},{"name":"Gramthan Rural Municipality"},{"name":"Dhanpalthan Rural Municipality"},{"name":"Kerabari Rural Municipality"},{"name":"Budhiganga Rural Municipality"},{"name":"Kanepokhari Rural Municipality"},{"name":"Miklajung Rural Municipality"},{"name":"Letang Municipality"},{"name":"Sunwarshi Municipality"},{"name":"Rangeli Municipality"},{"name":"Patahrishanishchare Municipality"},{"name":"Biratnagar Metropolitian City"},{"name":"Uralabari Municipality"},{"name":"Belbari Municipality"},{"name":"Sundarharaicha Municipality"},{"name":"Ratuwamai Municipality"}],"P1__Okhaldhunga":[{"name":"Likhu Rural Municipality"},{"name":"Molung Rural Municipality"},{"name":"Sunkoshi Rural Municipality"},{"name":"Champadevi Rural Municipality"},{"name":"Chisankhugadhi Rural Municipality"},{"name":"Khijidemba Rural Municipality"},{"name":"Manebhanjyang Rural Municipality"},{"name":"Siddhicharan Municipality"}],"P1__Panchthar":[{"name":"Yangwarak Rural Municipality"},{"name":"Hilihang Rural Municipality"},{"name":"Falelung Rural Municipality"},{"name":"Tumbewa Rural Municipality"},{"name":"Kummayak Rural Municipality"},{"name":"Miklajung Rural Municipality"},{"name":"Falgunanda Rural Municipality"},{"name":"Phidim Municipality"}],"P1__Sankhuwasabha":[{"name":"Makalu Rural Municipality"},{"name":"Chichila Rural Municipality"},{"name":"Silichong Rural Municipality"},{"name":"Bhotkhola Rural Municipality"},{"name":"Sabhapokhari Rural Municipality"},{"name":"Dharmadevi Municipality"},{"name":"Madi Municipality"},{"name":"Panchakhapan Municipality"},{"name":"Chainpur Municipality"},{"name":"Khandbari Municipality"}],"P1__Solukhumbu":[{"name":"Sotang Rural Municipality"},{"name":"Mahakulung Rural Municipality"},{"name":"Likhupike Rural Municipality"},{"name":"Nechasalyan Rural Municipality"},{"name":"Thulung Dudhkoshi Rural Municipality"},{"name":"Maapya Dudhkoshi Rural Municipality"},{"name":"Khumbupasanglahmu Rural Municipality"},{"name":"Solududhakunda Municipality"}],"P1__Sunsari":[{"name":"Gadhi Rural Municipality"},{"name":"Koshi Rural Municipality"},{"name":"Barju Rural Municipality"},{"name":"Harinagar Rural Municipality"},{"name":"Dewanganj Rural Municipality"},{"name":"Bhokraha Narsing Rural Municipality"},{"name":"Ramdhuni Municipality"},{"name":"Barahchhetra Municipality"},{"name":"Duhabi Municipality"},{"name":"Inaruwa Municipality"},{"name":"Dharan Sub-metropolitian City"},{"name":"Itahari Sub-metropolitian City"}],"P1__Taplejung":[{"name":"Sidingba Rural Municipality"},{"name":"Meringden Rural Municipality"},{"name":"Maiwakhola Rural Municipality"},{"name":"Phaktanglung Rural Municipality"},{"name":"Sirijangha Rural Municipality"},{"name":"Mikwakhola Rural Municipality"},{"name":"Aathrai Tribeni Rural Municipality"},{"name":"Pathivara Yangwarak Rural Municipality"},{"name":"Phungling Municipality"}],"P1__Tehrathum":[{"name":"Chhathar Rural Municipality"},{"name":"Phedap Rural Municipality"},{"name":"Aathrai Rural Municipality"},{"name":"Menchayam Rural Municipality"},{"name":"Laligurans Municipality"},{"name":"Myanglung Municipality"}],"P1__Udayapur":[{"name":"Tapli Rural Municipality"},{"name":"Rautamai Rural Municipality"},{"name":"Udayapurgadhi Rural Municipality"},{"name":"Limchungbung Rural Municipality"},{"name":"Chaudandigadhi Municipality"},{"name":"Triyuga Municipality"},{"name":"Katari Municipality"},{"name":"Belaka Municipality"}],"P2__Sarlahi":[{"name":"Dhankaul Rural Municipality"},{"name":"Parsa Rural Municipality"},{"name":"Bishnu Rural Municipality"},{"name":"Ramnagar Rural Municipality"},{"name":"Kaudena Rural Municipality"},{"name":"Basbariya Rural Municipality"},{"name":"Chandranagar Rural Municipality"},{"name":"Chakraghatta Rural Municipality"},{"name":"Bramhapuri Rural Municipality"},{"name":"Barahathawa Municipality"},{"name":"Haripur Municipality"},{"name":"Ishworpur Municipality"},{"name":"Lalbandi Municipality"},{"name":"Malangawa Municipality"},{"name":"Kabilasi Municipality"},{"name":"Bagmati Municipality"},{"name":"Hariwan Municipality"},{"name":"Balara Municipality"},{"name":"Haripurwa Municipality"},{"name":"Godaita Municipality"}],"P2__Dhanusha":[{"name":"Aaurahi Rural Municipality"},{"name":"Dhanauji Rural Municipality"},{"name":"Bateshwor Rural Municipality"},{"name":"Janaknandani Rural Municipality"},{"name":"Lakshminiya Rural Municipality"},{"name":"Mukhiyapatti Musarmiya Rural Municipality"},{"name":"Mithila Bihari Municipality"},{"name":"Kamala Municipality"},{"name":"Nagarain Municipality"},{"name":"Ganeshman Charnath Municipality"},{"name":"Mithila Municipality"},{"name":"Dhanusadham Municipality"},{"name":"Bideha Municipality"},{"name":"Sabaila Municipality"},{"name":"Hansapur Municipality"},{"name":"Janakpurdham Sub-metropolitian City"},{"name":"Sahidnagar Municipality"},{"name":"Chhireshwornath Municipality"}],"P2__Bara":[{"name":"Pheta Rural Municipality"},{"name":"Devtal Rural Municipality"},{"name":"Prasauni Rural Municipality"},{"name":"Suwarna Rural Municipality"},{"name":"Baragadhi Rural Municipality"},{"name":"Karaiyamai Rural Municipality"},{"name":"Parwanipur Rural Municipality"},{"name":"Bishrampur Rural Municipality"},{"name":"Adarshkotwal Rural Municipality"},{"name":"Jitpur Simara Sub-metropolitian City"},{"name":"Kalaiya Sub-metropolitian City"},{"name":"Pacharauta Municipality"},{"name":"Nijgadh Municipality"},{"name":"Simraungadh Municipality"},{"name":"Mahagadhimai Municipality"},{"name":"Kolhabi Municipality"}],"P2__Rautahat":[{"name":"Yemunamai Rural Municipality"},{"name":"Durga Bhagwati Rural Municipality"},{"name":"Katahariya Municipality"},{"name":"Maulapur Municipality"},{"name":"Madhav Narayan Municipality"},{"name":"Gaur Municipality"},{"name":"Gujara Municipality"},{"name":"Garuda Municipality"},{"name":"Ishanath Municipality"},{"name":"Chandrapur Municipality"},{"name":"Dewahhi Gonahi Municipality"},{"name":"Brindaban Municipality"},{"name":"Rajpur Municipality"},{"name":"Rajdevi Municipality"},{"name":"Gadhimai Municipality"},{"name":"Phatuwa Bijayapur Municipality"},{"name":"Baudhimai Municipality"},{"name":"Paroha Municipality"}],"P2__Saptari":[{"name":"Rajgadh Rural Municipality"},{"name":"Rupani Rural Municipality"},{"name":"Tirahut Rural Municipality"},{"name":"Mahadeva Rural Municipality"},{"name":"Bishnupur Rural Municipality"},{"name":"Chhinnamasta Rural Municipality"},{"name":"Balan Bihul Rural Municipality"},{"name":"Tilathi Koiladi Rural Municipality"},{"name":"Agnisair Krishna Savaran Rural Municipality"},{"name":"Hanumannagar Kankalini Municipality"},{"name":"Kanchanrup Municipality"},{"name":"Rajbiraj Municipality"},{"name":"Khadak Municipality"},{"name":"Dakneshwori Municipality"},{"name":"Saptakoshi Rural Municipality"},{"name":"Surunga Municipality"},{"name":"Shambhunath Municipality"},{"name":"Bode Barsain Municipality"}],"P2__Siraha":[{"name":"Aurahi Rural Municipality"},{"name":"Naraha Rural Municipality"},{"name":"Arnama Rural Municipality"},{"name":"Bhagawanpur Rural Municipality"},{"name":"Nawarajpur Rural Municipality"},{"name":"Bishnupur Rural Municipality"},{"name":"Bariyarpatti Rural Municipality"},{"name":"Laxmipur Patari Rural Municipality"},{"name":"Sakhuwanankarkatti Rural Municipality"},{"name":"Mirchaiya Municipality"},{"name":"Lahan Municipality"},{"name":"Siraha Municipality"},{"name":"Dhangadhimai Municipality"},{"name":"Kalyanpur Municipality"},{"name":"Karjanha Municipality"},{"name":"Golbazar Municipality"},{"name":"Sukhipur Municipality"}],"P2__Mahottari":[{"name":"Pipra Rural Municipality"},{"name":"Sonama Rural Municipality"},{"name":"Samsi Rural Municipality"},{"name":"Ekdanra Rural Municipality"},{"name":"Mahottari Rural Municipality"},{"name":"Gaushala Municipality"},{"name":"Ramgopalpur Municipality"},{"name":"Aurahi Municipality"},{"name":"Bardibas Municipality"},{"name":"Bhangaha Municipality"},{"name":"Jaleswor Municipality"},{"name":"Balwa Municipality"},{"name":"Manra Siswa Municipality"},{"name":"Matihani Municipality"},{"name":"Loharpatti Municipality"}],"P2__Parsa":[{"name":"Thori Rural Municipality"},{"name":"Dhobini Rural Municipality"},{"name":"Chhipaharmai Rural Municipality"},{"name":"Jirabhawani Rural Municipality"},{"name":"Jagarnathpur Rural Municipality"},{"name":"Kalikamai Rural Municipality"},{"name":"Bindabasini Rural Municipality"},{"name":"Pakahamainpur Rural Municipality"},{"name":"Sakhuwaprasauni Rural Municipality"},{"name":"Paterwasugauli Rural Municipality"},{"name":"Birgunj Metropolitian City"},{"name":"Bahudaramai Municipality"},{"name":"Pokhariya Municipality"},{"name":"Parsagadhi Municipality"}],"P2__Parasi":[{"name":"Sarawal Rural Municipality"},{"name":"Susta Rural Municipality"},{"name":"Pratappur Rural Municipality"},{"name":"Palhi Nandan Rural Municipality"},{"name":"Bardaghat Municipality"},{"name":"Sunwal Municipality"},{"name":"Ramgram Municipality"}],"P4__Baglung":[{"name":"Bareng Rural Municipality"},{"name":"Badigad Rural Municipality"},{"name":"Nisikhola Rural Municipality"},{"name":"Kanthekhola Rural Municipality"},{"name":"Tara Khola Rural Municipality"},{"name":"Taman Khola Rural Municipality"},{"name":"Jaimuni Municipality"},{"name":"Baglung Municipality"},{"name":"Galkot Municipality"},{"name":"Dhorpatan Municipality"}],"P4__Gorkha":[{"name":"Gandaki Rural Municipality"},{"name":"Dharche Rural Municipality"},{"name":"Aarughat Rural Municipality"},{"name":"Ajirkot Rural Municipality"},{"name":"Sahid Lakhan Rural Municipality"},{"name":"Siranchok Rural Municipality"},{"name":"Bhimsenthapa Rural Municipality"},{"name":"Chum Nubri Rural Municipality"},{"name":"Barpak Sulikot Rural Municipality"},{"name":"Palungtar Municipality"},{"name":"Gorkha Municipality"}],"P4__Kaski":[{"name":"Rupa Rural Municipality"},{"name":"Madi Rural Municipality"},{"name":"Annapurna Rural Municipality"},{"name":"Machhapuchchhre Rural Municipality"},{"name":"Pokhara Metropolitian City"}],"P4__Lamjung":[{"name":"Dordi Rural Municipality"},{"name":"Dudhpokhari Rural Municipality"},{"name":"Marsyangdi Rural Municipality"},{"name":"Kwholasothar Rural Municipality"},{"name":"Sundarbazar Municipality"},{"name":"Besishahar Municipality"},{"name":"Rainas Municipality"},{"name":"Madhyanepal Municipality"}],"P4__Manang":[{"name":"Chame Rural Municipality"},{"name":"Narshon Rural Municipality"},{"name":"Narpa Bhumi Rural Municipality"},{"name":"Manang Ingshyang Rural Municipality"}],"P4__Mustang":[{"name":"Thasang Rural Municipality"},{"name":"Gharapjhong Rural Municipality"},{"name":"Lomanthang Rural Municipality"},{"name":"Lo-ghekar Damodarkunda Rural Municipality"},{"name":"Waragung Muktikhsetra Rural Municipality"}],"P4__Myagdi":[{"name":"Mangala Rural Municipality"},{"name":"Malika Rural Municipality"},{"name":"Raghuganga Rural Municipality"},{"name":"Dhaulagiri Rural Municipality"},{"name":"Annapurna Rural Municipality"},{"name":"Beni Municipality"}],"P4__Nawalpur":[{"name":"Baudeekali Rural Municipality"},{"name":"Bulingtar Rural Municipality"},{"name":"Hupsekot Rural Municipality"},{"name":"Binayee Tribeni Rural Municipality"},{"name":"Madhyabindu Municipality"},{"name":"Devchuli Municipality"},{"name":"Gaidakot Municipality"},{"name":"Kawasoti Municipality"}],"P4__Parbat":[{"name":"Modi Rural Municipality"},{"name":"Painyu Rural Municipality"},{"name":"Jaljala Rural Municipality"},{"name":"Bihadi Rural Municipality"},{"name":"Mahashila Rural Municipality"},{"name":"Kushma Municipality"},{"name":"Phalebas Municipality"}],"P4__Syangja":[{"name":"Harinas Rural Municipality"},{"name":"Biruwa Rural Municipality"},{"name":"Aandhikhola Rural Municipality"},{"name":"Phedikhola Rural Municipality"},{"name":"Kaligandagi Rural Municipality"},{"name":"Arjunchaupari Rural Municipality"},{"name":"Putalibazar Municipality"},{"name":"Bhirkot Municipality"},{"name":"Galyang Municipality"},{"name":"Chapakot Municipality"},{"name":"Waling Municipality"}],"P4__Tanahun":[{"name":"Ghiring Rural Municipality"},{"name":"Devghat Rural Municipality"},{"name":"Rhishing Rural Municipality"},{"name":"Myagde Rural Municipality"},{"name":"Bandipur Rural Municipality"},{"name":"Anbukhaireni Rural Municipality"},{"name":"Byas Municipality"},{"name":"Shuklagandaki Municipality"},{"name":"Bhimad Municipality"},{"name":"Bhanu Municipality"}],"P6__Western-rukum":[{"name":"Tribeni Rural Municipality"},{"name":"Sani Bheri Rural Municipality"},{"name":"Banfikot Rural Municipality"},{"name":"Aathbiskot Municipality"},{"name":"Chaurjahari Municipality"},{"name":"Musikot Municipality"}],"P6__Salyan":[{"name":"Kumakh Rural Municipality"},{"name":"Darma Rural Municipality"},{"name":"Kapurkot Rural Municipality"},{"name":"Kalimati Rural Municipality"},{"name":"Tribeni Rural Municipality"},{"name":"Chhatreshwori Rural Municipality"},{"name":"Siddha Kumakh Rural Municipality"},{"name":"Sharada Municipality"},{"name":"Bangad Kupinde Municipality"},{"name":"Bagchaur Municipality"}],"P6__Dolpa":[{"name":"Kaike Rural Municipality"},{"name":"Jagadulla Rural Municipality"},{"name":"Mudkechula Rural Municipality"},{"name":"Dolpo Buddha Rural Municipality"},{"name":"Shey Phoksundo Rural Municipality"},{"name":"Chharka Tangsong Rural Municipality"},{"name":"Tripurasundari Municipality"},{"name":"Thuli Bheri Municipality"}],"P6__Humla":[{"name":"Simkot Rural Municipality"},{"name":"Namkha Rural Municipality"},{"name":"Chankheli Rural Municipality"},{"name":"Tanjakot Rural Municipality"},{"name":"Sarkegad Rural Municipality"},{"name":"Adanchuli Rural Municipality"},{"name":"Kharpunath Rural Municipality"}],"P6__Jumla":[{"name":"Hima Rural Municipality"},{"name":"Tila Rural Municipality"},{"name":"Sinja Rural Municipality"},{"name":"Guthichaur Rural Municipality"},{"name":"Tatopani Rural Municipality"},{"name":"Patrasi Rural Municipality"},{"name":"Kanakasundari Rural Municipality"},{"name":"Chandannath Municipality"}],"P6__Kalikot":[{"name":"Mahawai Rural Municipality"},{"name":"Palata Rural Municipality"},{"name":"Naraharinath Rural Municipality"},{"name":"Pachaljharana Rural Municipality"},{"name":"Subha Kalika Rural Municipality"},{"name":"Sanni Tribeni Rural Municipality"},{"name":"Khandachakra Municipality"},{"name":"Raskot Municipality"},{"name":"Tilagufa Municipality"}],"P6__Mugu":[{"name":"Soru Rural Municipality"},{"name":"Khatyad Rural Municipality"},{"name":"Mugum Karmarong Rural Municipality"},{"name":"Chhayanath Rara Municipality"}],"P6__Surkhet":[{"name":"Chaukune Rural Municipality"},{"name":"Simta Rural Municipality"},{"name":"Chingad Rural Municipality"},{"name":"Barahtal Rural Municipality"},{"name":"Gurbhakot Municipality"},{"name":"Panchpuri Municipality"},{"name":"Bheriganga Municipality"},{"name":"Lekbeshi Municipality"},{"name":"Birendranagar Municipality"}],"P6__Dailekh":[{"name":"Bhairabi Rural Municipality"},{"name":"Mahabu Rural Municipality"},{"name":"Gurans Rural Municipality"},{"name":"Naumule Rural Municipality"},{"name":"Bhagawatimai Rural Municipality"},{"name":"Thantikandh Rural Municipality"},{"name":"Dungeshwor Rural Municipality"},{"name":"Aathabis Municipality"},{"name":"Dullu Municipality"},{"name":"Chamunda Bindrasaini Municipality"},{"name":"Narayan Municipality"}],"P6__Jajarkot":[{"name":"Kuse Rural Municipality"},{"name":"Shiwalaya Rural Municipality"},{"name":"Barekot Rural Municipality"},{"name":"Junichande Rural Municipality"},{"name":"Nalagad Municipality"},{"name":"Bheri Municipality"},{"name":"Chhedagad Municipality"}]}}